wdldoc/__init__.py
wdldoc/__main__.py
wdldoc/bin/__init__.py
wdldoc/bin/wdldoc.py
wdldoc/miniwdl/__init__.py
wdldoc/miniwdl/sources.py
wdldoc/templates/markdown.py
wdldoc-1.7.1.dist-info/entry_points.txt
wdldoc-1.7.1.dist-info/LICENSE.md
wdldoc-1.7.1.dist-info/WHEEL
wdldoc-1.7.1.dist-info/METADATA
wdldoc-1.7.1.dist-info/RECORD
