Metadata-Version: 2.1
Name: wdldoc
Version: 1.7.1
Summary: Create WDL documentation using Markdown.
Home-page: https://github.com/stjudecloud/wdldoc
License: MIT
Keywords: bioinformatics,genomics,workflows,cromwell
Author: Clay McLeod
Author-email: Clay.McLeod@STJUDE.org
Requires-Python: >=3.8,<4.0
Classifier: Development Status :: 5 - Production/Stable
Classifier: License :: OSI Approved :: MIT License
Classifier: Operating System :: OS Independent
Classifier: Programming Language :: Python :: 3
Classifier: Programming Language :: Python :: 3.8
Classifier: Topic :: Scientific/Engineering :: Bio-Informatics
Requires-Dist: cachecontrol[filecache] (>=0.12.6,<0.13.0)
Requires-Dist: logzero (>=1.5.0,<2.0.0)
Requires-Dist: miniwdl (>=1.2.2,<2.0.0)
Requires-Dist: python-semantic-release (>=5.1.0,<6.0.0)
Requires-Dist: requests (>=2.23.0,<3.0.0)
Project-URL: Repository, https://github.com/stjudecloud/wdldoc
